python_tracer-1.0.1.dist-info/licenses/LICENSE
pytracer/__init__.py
pytracer/core.py
pytracer/decorators.py
pytracer/report.py
python_tracer-1.0.1.dist-info/METADATA
python_tracer-1.0.1.dist-info/WHEEL
python_tracer-1.0.1.dist-info/top_level.txt
python_tracer-1.0.1.dist-info/RECORD
