Metadata-Version: 2.4
Name: python-tracer
Version: 1.0.1
Summary: Python Tracer and Performance Monitoring Tool with HTML Reports
Home-page: https://github.com/gauraobharambe/python-tracer
Author: Gaurao Bharambe
Author-email: gaurao7793@gmail.com
License: MIT
Project-URL: Bug Tracker, https://github.com/gauraobharambe/python-tracer/issues
Classifier: Programming Language :: Python :: 3
Classifier: License :: OSI Approved :: MIT License
Classifier: Operating System :: OS Independent
Requires-Python: >=3.7
License-File: LICENSE
Provides-Extra: dev
Requires-Dist: pytest; extra == "dev"
Requires-Dist: setuptools-scm; extra == "dev"
Dynamic: license-file
